setup.py
lw_distributions/Binomialdistribution.py
lw_distributions/Gaussiandistribution.py
lw_distributions/Generaldistribution.py
lw_distributions/__init__.py
lw_distributions.egg-info/PKG-INFO
lw_distributions.egg-info/SOURCES.txt
lw_distributions.egg-info/dependency_links.txt
lw_distributions.egg-info/not-zip-safe
lw_distributions.egg-info/top_level.txt