Metadata-Version: 1.0
Name: lw-distributions
Version: 0.2
Summary: Gaussian and Binomial distributions
Home-page: UNKNOWN
Author: Leopold Walther
Author-email: UNKNOWN
License: UNKNOWN
Platform: UNKNOWN
